MANIFEST.in
README.md
setup.py
mocos_helper.egg-info/PKG-INFO
mocos_helper.egg-info/SOURCES.txt
mocos_helper.egg-info/dependency_links.txt
mocos_helper.egg-info/not-zip-safe
mocos_helper.egg-info/requires.txt
mocos_helper.egg-info/top_level.txt
src/__init__.py
src/random.py
src/cpp_code/Makefile
src/cpp_code/age_dep_sampler.h
src/cpp_code/btrd.h
src/cpp_code/libMocosHelper.so
src/cpp_code/libMocosHelper2.so
src/cpp_code/mocosMath.cpp
src/cpp_code/mocosMath.h
src/cpp_code/platform.h
src/cpp_code/test
src/cpp_code/test.cpp
src/cpp_code/unity_build.cpp
src/cpp_code/weighted_sampling.cpp
src/cpp_code/weighted_sampling.h