Metadata-Version: 2.1
Name: mocos-helper
Version: 0.0.16
Summary: Helper code for MOCOS-COVID19/modelling-ncov2019
Home-page: https://github.com/michalsta/mocos_helper
Author: Michał Startek, Mateusz Łącki
License: UNKNOWN
Keywords: covid-19 modelling
Platform: UNKNOWN
Classifier: Development Status :: 2 - Pre-Alpha
Classifier: Topic :: Scientific/Engineering :: Bio-Informatics
Classifier: License :: OSI Approved :: MIT License
Classifier: Programming Language :: Python :: 2
Classifier: Programming Language :: Python :: 2.7
Classifier: Programming Language :: Python :: 3
Classifier: Programming Language :: Python :: 3.5
Classifier: Programming Language :: Python :: 3.6
Classifier: Programming Language :: Python :: 3.7
Classifier: Programming Language :: Python :: 3.8
Requires-Python: >=2.7, !=3.0.*, !=3.1.*, !=3.2.*, !=3.3.*, !=3.4.*, <4
